{
  "sun": {
    "lon": 355.32281938897484,
    "sign": 11,
    "deg": 25,
    "min": 19,
    "retrograde": false
  },
  "moon": {
    "lon": 316.2383311183743,
    "sign": 10,
    "deg": 16,
    "min": 14,
    "retrograde": false
  },
  "mercury": {
    "lon": 339.72740731951586,
    "sign": 11,
    "deg": 9,
    "min": 43,
    "retrograde": true
  },
  "venus": {
    "lon": 11.761751889888133,
    "sign": 0,
    "deg": 11,
    "min": 45,
    "retrograde": false
  },
  "mars": {
    "lon": 340.4928739452836,
    "sign": 11,
    "deg": 10,
    "min": 29,
    "retrograde": false
  },
  "jupiter": {
    "lon": 105.12439116412563,
    "sign": 3,
    "deg": 15,
    "min": 7,
    "retrograde": false
  },
  "saturn": {
    "lon": 3.5429389763801846,
    "sign": 0,
    "deg": 3,
    "min": 32,
    "retrograde": false
  },
  "uranus": {
    "lon": 58.14185871906032,
    "sign": 1,
    "deg": 28,
    "min": 8,
    "retrograde": false
  },
  "neptune": {
    "lon": 1.595631483660827,
    "sign": 0,
    "deg": 1,
    "min": 35,
    "retrograde": false
  },
  "pluto": {
    "lon": 304.9039764909205,
    "sign": 10,
    "deg": 4,
    "min": 54,
    "retrograde": false
  },
  "ascendant": {
    "lon": 162.52297385065705,
    "sign": 5,
    "deg": 12,
    "min": 31,
    "retrograde": false
  },
  "medium_coeli": {
    "lon": 69.75692171049808,
    "sign": 2,
    "deg": 9,
    "min": 45,
    "retrograde": false
  }
}