{
  "sun": {
    "lon": 67.61269900550072,
    "sign": 2,
    "deg": 7,
    "min": 36,
    "retrograde": false
  },
  "moon": {
    "lon": 221.03377325995632,
    "sign": 7,
    "deg": 11,
    "min": 2,
    "retrograde": false
  },
  "mercury": {
    "lon": 83.69314156394886,
    "sign": 2,
    "deg": 23,
    "min": 41,
    "retrograde": false
  },
  "venus": {
    "lon": 101.78612717703578,
    "sign": 3,
    "deg": 11,
    "min": 47,
    "retrograde": false
  },
  "mars": {
    "lon": 37.494110197628466,
    "sign": 1,
    "deg": 7,
    "min": 29,
    "retrograde": false
  },
  "jupiter": {
    "lon": 113.49736885343269,
    "sign": 3,
    "deg": 23,
    "min": 29,
    "retrograde": false
  },
  "saturn": {
    "lon": 11.981551652254042,
    "sign": 0,
    "deg": 11,
    "min": 58,
    "retrograde": false
  },
  "uranus": {
    "lon": 61.88670943695382,
    "sign": 2,
    "deg": 1,
    "min": 53,
    "retrograde": false
  },
  "neptune": {
    "lon": 3.999674869567337,
    "sign": 0,
    "deg": 3,
    "min": 59,
    "retrograde": false
  },
  "pluto": {
    "lon": 305.39628743195055,
    "sign": 10,
    "deg": 5,
    "min": 23,
    "retrograde": true
  },
  "ascendant": {
    "lon": 229.78139327086086,
    "sign": 7,
    "deg": 19,
    "min": 46,
    "retrograde": false
  },
  "medium_coeli": {
    "lon": 150.7682335830823,
    "sign": 5,
    "deg": 0,
    "min": 46,
    "retrograde": false
  }
}