{
  "sun": {
    "lon": 355.0148348592172,
    "sign": 11,
    "deg": 25,
    "min": 0,
    "retrograde": false
  },
  "moon": {
    "lon": 312.2740446846326,
    "sign": 10,
    "deg": 12,
    "min": 16,
    "retrograde": false
  },
  "mercury": {
    "lon": 339.8898020115674,
    "sign": 11,
    "deg": 9,
    "min": 53,
    "retrograde": true
  },
  "venus": {
    "lon": 11.378452338942752,
    "sign": 0,
    "deg": 11,
    "min": 22,
    "retrograde": false
  },
  "mars": {
    "lon": 340.2496520630934,
    "sign": 11,
    "deg": 10,
    "min": 14,
    "retrograde": false
  },
  "jupiter": {
    "lon": 105.11976011677,
    "sign": 3,
    "deg": 15,
    "min": 7,
    "retrograde": false
  },
  "saturn": {
    "lon": 3.504619002990259,
    "sign": 0,
    "deg": 3,
    "min": 30,
    "retrograde": false
  },
  "uranus": {
    "lon": 58.13166859007774,
    "sign": 1,
    "deg": 28,
    "min": 7,
    "retrograde": false
  },
  "neptune": {
    "lon": 1.5839692255672595,
    "sign": 0,
    "deg": 1,
    "min": 35,
    "retrograde": false
  },
  "pluto": {
    "lon": 304.8970233241431,
    "sign": 10,
    "deg": 4,
    "min": 53,
    "retrograde": false
  },
  "ascendant": {
    "lon": 67.69557698872325,
    "sign": 2,
    "deg": 7,
    "min": 41,
    "retrograde": false
  },
  "medium_coeli": {
    "lon": 314.081754012793,
    "sign": 10,
    "deg": 14,
    "min": 4,
    "retrograde": false
  }
}