{
  "sun": {
    "lon": 6.6082714756619545,
    "sign": 0,
    "deg": 6,
    "min": 36,
    "retrograde": false
  },
  "moon": {
    "lon": 115.69013504021954,
    "sign": 3,
    "deg": 25,
    "min": 41,
    "retrograde": false
  },
  "mercury": {
    "lon": 340.36905618456314,
    "sign": 11,
    "deg": 10,
    "min": 22,
    "retrograde": false
  },
  "venus": {
    "lon": 25.81966742906072,
    "sign": 0,
    "deg": 25,
    "min": 49,
    "retrograde": false
  },
  "mars": {
    "lon": 349.41920712396495,
    "sign": 11,
    "deg": 19,
    "min": 25,
    "retrograde": false
  },
  "jupiter": {
    "lon": 105.50580463328292,
    "sign": 3,
    "deg": 15,
    "min": 30,
    "retrograde": false
  },
  "saturn": {
    "lon": 4.959003014053058,
    "sign": 0,
    "deg": 4,
    "min": 57,
    "retrograde": false
  },
  "uranus": {
    "lon": 58.56210617585201,
    "sign": 1,
    "deg": 28,
    "min": 33,
    "retrograde": false
  },
  "neptune": {
    "lon": 2.0260342741312245,
    "sign": 0,
    "deg": 2,
    "min": 1,
    "retrograde": false
  },
  "pluto": {
    "lon": 305.1351140656723,
    "sign": 10,
    "deg": 5,
    "min": 8,
    "retrograde": false
  },
  "ascendant": {
    "lon": 277.564425492301,
    "sign": 9,
    "deg": 7,
    "min": 33,
    "retrograde": false
  },
  "medium_coeli": {
    "lon": 211.4521324846004,
    "sign": 7,
    "deg": 1,
    "min": 27,
    "retrograde": false
  }
}