{
  "sun": {
    "lon": 29.07420418996983,
    "sign": 0,
    "deg": 29,
    "min": 4,
    "retrograde": false
  },
  "moon": {
    "lon": 51.66967848232025,
    "sign": 1,
    "deg": 21,
    "min": 40,
    "retrograde": false
  },
  "mercury": {
    "lon": 5.838120216709014,
    "sign": 0,
    "deg": 5,
    "min": 50,
    "retrograde": false
  },
  "venus": {
    "lon": 53.851654392432636,
    "sign": 1,
    "deg": 23,
    "min": 51,
    "retrograde": false
  },
  "mars": {
    "lon": 7.225031354368047,
    "sign": 0,
    "deg": 7,
    "min": 13,
    "retrograde": false
  },
  "jupiter": {
    "lon": 107.40993194498452,
    "sign": 3,
    "deg": 17,
    "min": 24,
    "retrograde": false
  },
  "saturn": {
    "lon": 7.76549287201628,
    "sign": 0,
    "deg": 7,
    "min": 45,
    "retrograde": false
  },
  "uranus": {
    "lon": 59.63134889905634,
    "sign": 1,
    "deg": 29,
    "min": 37,
    "retrograde": false
  },
  "neptune": {
    "lon": 2.863443284795102,
    "sign": 0,
    "deg": 2,
    "min": 51,
    "retrograde": false
  },
  "pluto": {
    "lon": 305.4381261350554,
    "sign": 10,
    "deg": 5,
    "min": 26,
    "retrograde": false
  },
  "ascendant": {
    "lon": 248.13948057057465,
    "sign": 8,
    "deg": 8,
    "min": 8,
    "retrograde": false
  },
  "medium_coeli": {
    "lon": 175.44205420475666,
    "sign": 5,
    "deg": 25,
    "min": 26,
    "retrograde": false
  }
}