{
  "sun": {
    "lon": 8.041441393990228,
    "sign": 0,
    "deg": 8,
    "min": 2,
    "retrograde": false
  },
  "moon": {
    "lon": 135.44122843751978,
    "sign": 4,
    "deg": 15,
    "min": 26,
    "retrograde": false
  },
  "mercury": {
    "lon": 341.23979888016186,
    "sign": 11,
    "deg": 11,
    "min": 14,
    "retrograde": false
  },
  "venus": {
    "lon": 27.60680457629703,
    "sign": 0,
    "deg": 27,
    "min": 36,
    "retrograde": false
  },
  "mars": {
    "lon": 350.55453405852427,
    "sign": 11,
    "deg": 20,
    "min": 33,
    "retrograde": false
  },
  "jupiter": {
    "lon": 105.5831798333487,
    "sign": 3,
    "deg": 15,
    "min": 34,
    "retrograde": false
  },
  "saturn": {
    "lon": 5.13977868267607,
    "sign": 0,
    "deg": 5,
    "min": 8,
    "retrograde": false
  },
  "uranus": {
    "lon": 58.62168395490296,
    "sign": 1,
    "deg": 28,
    "min": 37,
    "retrograde": false
  },
  "neptune": {
    "lon": 2.0808079230925975,
    "sign": 0,
    "deg": 2,
    "min": 4,
    "retrograde": false
  },
  "pluto": {
    "lon": 305.16098323208166,
    "sign": 10,
    "deg": 5,
    "min": 9,
    "retrograde": false
  },
  "ascendant": {
    "lon": 118.35924472995154,
    "sign": 3,
    "deg": 28,
    "min": 21,
    "retrograde": false
  },
  "medium_coeli": {
    "lon": 13.290476922676492,
    "sign": 0,
    "deg": 13,
    "min": 17,
    "retrograde": false
  }
}