{
  "sun": {
    "lon": 49.79678336063128,
    "sign": 1,
    "deg": 19,
    "min": 47,
    "retrograde": false
  },
  "moon": {
    "lon": 326.36389893856716,
    "sign": 10,
    "deg": 26,
    "min": 21,
    "retrograde": false
  },
  "mercury": {
    "lon": 44.86246283957048,
    "sign": 1,
    "deg": 14,
    "min": 51,
    "retrograde": false
  },
  "venus": {
    "lon": 79.6914999101991,
    "sign": 2,
    "deg": 19,
    "min": 41,
    "retrograde": false
  },
  "mars": {
    "lon": 23.582778724808147,
    "sign": 0,
    "deg": 23,
    "min": 34,
    "retrograde": false
  },
  "jupiter": {
    "lon": 110.31736125275981,
    "sign": 3,
    "deg": 20,
    "min": 19,
    "retrograde": false
  },
  "saturn": {
    "lon": 10.180527883625068,
    "sign": 0,
    "deg": 10,
    "min": 10,
    "retrograde": false
  },
  "uranus": {
    "lon": 60.8096829352048,
    "sign": 2,
    "deg": 0,
    "min": 48,
    "retrograde": false
  },
  "neptune": {
    "lon": 3.543156016279365,
    "sign": 0,
    "deg": 3,
    "min": 32,
    "retrograde": false
  },
  "pluto": {
    "lon": 305.50601019943605,
    "sign": 10,
    "deg": 5,
    "min": 30,
    "retrograde": true
  },
  "ascendant": {
    "lon": 65.76617605805664,
    "sign": 2,
    "deg": 5,
    "min": 45,
    "retrograde": false
  },
  "medium_coeli": {
    "lon": 312.3752461156162,
    "sign": 10,
    "deg": 12,
    "min": 22,
    "retrograde": false
  }
}