{
  "sun": {
    "lon": 114.81737848326699,
    "sign": 3,
    "deg": 24,
    "min": 49,
    "retrograde": false
  },
  "moon": {
    "lon": 155.14711468069908,
    "sign": 5,
    "deg": 5,
    "min": 8,
    "retrograde": false
  },
  "mercury": {
    "lon": 108.14473156125982,
    "sign": 3,
    "deg": 18,
    "min": 8,
    "retrograde": true
  },
  "venus": {
    "lon": 158.4435513721361,
    "sign": 5,
    "deg": 8,
    "min": 26,
    "retrograde": false
  },
  "mars": {
    "lon": 73.05714587950516,
    "sign": 2,
    "deg": 13,
    "min": 3,
    "retrograde": false
  },
  "jupiter": {
    "lon": 123.72605728525079,
    "sign": 4,
    "deg": 3,
    "min": 43,
    "retrograde": false
  },
  "saturn": {
    "lon": 14.673955864694054,
    "sign": 0,
    "deg": 14,
    "min": 40,
    "retrograde": false
  },
  "uranus": {
    "lon": 64.46334226190282,
    "sign": 2,
    "deg": 4,
    "min": 27,
    "retrograde": false
  },
  "neptune": {
    "lon": 4.391763496882611,
    "sign": 0,
    "deg": 4,
    "min": 23,
    "retrograde": true
  },
  "pluto": {
    "lon": 304.5165930131104,
    "sign": 10,
    "deg": 4,
    "min": 30,
    "retrograde": true
  },
  "ascendant": {
    "lon": 103.23969578518977,
    "sign": 3,
    "deg": 13,
    "min": 14,
    "retrograde": false
  },
  "medium_coeli": {
    "lon": 353.23293726647546,
    "sign": 11,
    "deg": 23,
    "min": 13,
    "retrograde": false
  }
}