{
  "sun": {
    "lon": 356.576398040369,
    "sign": 11,
    "deg": 26,
    "min": 34,
    "retrograde": false
  },
  "moon": {
    "lon": 332.72635457242114,
    "sign": 11,
    "deg": 2,
    "min": 43,
    "retrograde": false
  },
  "mercury": {
    "lon": 339.1692393541449,
    "sign": 11,
    "deg": 9,
    "min": 10,
    "retrograde": true
  },
  "venus": {
    "lon": 13.322048566236356,
    "sign": 0,
    "deg": 13,
    "min": 19,
    "retrograde": false
  },
  "mars": {
    "lon": 341.4830730039497,
    "sign": 11,
    "deg": 11,
    "min": 28,
    "retrograde": false
  },
  "jupiter": {
    "lon": 105.14642312495961,
    "sign": 3,
    "deg": 15,
    "min": 8,
    "retrograde": false
  },
  "saturn": {
    "lon": 3.6991382021425383,
    "sign": 0,
    "deg": 3,
    "min": 41,
    "retrograde": false
  },
  "uranus": {
    "lon": 58.18404644811538,
    "sign": 1,
    "deg": 28,
    "min": 11,
    "retrograde": false
  },
  "neptune": {
    "lon": 1.6431620524203105,
    "sign": 0,
    "deg": 1,
    "min": 38,
    "retrograde": false
  },
  "pluto": {
    "lon": 304.93192804439917,
    "sign": 10,
    "deg": 4,
    "min": 55,
    "retrograde": false
  },
  "ascendant": {
    "lon": 237.3104551850155,
    "sign": 7,
    "deg": 27,
    "min": 18,
    "retrograde": false
  },
  "medium_coeli": {
    "lon": 160.86594475094032,
    "sign": 5,
    "deg": 10,
    "min": 51,
    "retrograde": false
  }
}