{
  "sun": {
    "lon": 92.06577985942364,
    "sign": 3,
    "deg": 2,
    "min": 3,
    "retrograde": false
  },
  "moon": {
    "lon": 200.63364661691557,
    "sign": 6,
    "deg": 20,
    "min": 38,
    "retrograde": false
  },
  "mercury": {
    "lon": 114.78476081080777,
    "sign": 3,
    "deg": 24,
    "min": 47,
    "retrograde": false
  },
  "venus": {
    "lon": 131.64924453873337,
    "sign": 4,
    "deg": 11,
    "min": 38,
    "retrograde": false
  },
  "mars": {
    "lon": 56.20642169978445,
    "sign": 1,
    "deg": 26,
    "min": 12,
    "retrograde": false
  },
  "jupiter": {
    "lon": 118.5746345356172,
    "sign": 3,
    "deg": 28,
    "min": 34,
    "retrograde": false
  },
  "saturn": {
    "lon": 13.821780848928038,
    "sign": 0,
    "deg": 13,
    "min": 49,
    "retrograde": false
  },
  "uranus": {
    "lon": 63.322094203077036,
    "sign": 2,
    "deg": 3,
    "min": 19,
    "retrograde": false
  },
  "neptune": {
    "lon": 4.364818943709968,
    "sign": 0,
    "deg": 4,
    "min": 21,
    "retrograde": false
  },
  "pluto": {
    "lon": 305.0229046799282,
    "sign": 10,
    "deg": 5,
    "min": 1,
    "retrograde": true
  },
  "ascendant": {
    "lon": 126.14925935263702,
    "sign": 4,
    "deg": 6,
    "min": 8,
    "retrograde": false
  },
  "medium_coeli": {
    "lon": 23.79062963423278,
    "sign": 0,
    "deg": 23,
    "min": 47,
    "retrograde": false
  }
}