{
  "sun": {
    "lon": 29.584630661592648,
    "sign": 0,
    "deg": 29,
    "min": 35,
    "retrograde": false
  },
  "moon": {
    "lon": 59.47476354952948,
    "sign": 1,
    "deg": 29,
    "min": 28,
    "retrograde": false
  },
  "mercury": {
    "lon": 6.638410153776269,
    "sign": 0,
    "deg": 6,
    "min": 38,
    "retrograde": false
  },
  "venus": {
    "lon": 54.48863397954889,
    "sign": 1,
    "deg": 24,
    "min": 29,
    "retrograde": false
  },
  "mars": {
    "lon": 7.629151528996561,
    "sign": 0,
    "deg": 7,
    "min": 37,
    "retrograde": false
  },
  "jupiter": {
    "lon": 107.46939042344509,
    "sign": 3,
    "deg": 17,
    "min": 28,
    "retrograde": false
  },
  "saturn": {
    "lon": 7.827770091056761,
    "sign": 0,
    "deg": 7,
    "min": 49,
    "retrograde": false
  },
  "uranus": {
    "lon": 59.65861125212735,
    "sign": 1,
    "deg": 29,
    "min": 39,
    "retrograde": false
  },
  "neptune": {
    "lon": 2.8815993524546695,
    "sign": 0,
    "deg": 2,
    "min": 52,
    "retrograde": false
  },
  "pluto": {
    "lon": 305.4423326454518,
    "sign": 10,
    "deg": 5,
    "min": 26,
    "retrograde": false
  },
  "ascendant": {
    "lon": 111.98136590014329,
    "sign": 3,
    "deg": 21,
    "min": 58,
    "retrograde": false
  },
  "medium_coeli": {
    "lon": 4.719321954482371,
    "sign": 0,
    "deg": 4,
    "min": 43,
    "retrograde": false
  }
}