{
  "sun": {
    "lon": 73.30969981427343,
    "sign": 2,
    "deg": 13,
    "min": 18,
    "retrograde": false
  },
  "moon": {
    "lon": 291.8566757196582,
    "sign": 9,
    "deg": 21,
    "min": 51,
    "retrograde": false
  },
  "mercury": {
    "lon": 93.92724369947109,
    "sign": 3,
    "deg": 3,
    "min": 55,
    "retrograde": false
  },
  "venus": {
    "lon": 108.80676451525949,
    "sign": 3,
    "deg": 18,
    "min": 48,
    "retrograde": false
  },
  "mars": {
    "lon": 41.90011371461523,
    "sign": 1,
    "deg": 11,
    "min": 54,
    "retrograde": false
  },
  "jupiter": {
    "lon": 114.61848893155762,
    "sign": 3,
    "deg": 24,
    "min": 37,
    "retrograde": false
  },
  "saturn": {
    "lon": 12.483933949177075,
    "sign": 0,
    "deg": 12,
    "min": 29,
    "retrograde": false
  },
  "uranus": {
    "lon": 62.23116886444729,
    "sign": 2,
    "deg": 2,
    "min": 13,
    "retrograde": false
  },
  "neptune": {
    "lon": 4.11405474280915,
    "sign": 0,
    "deg": 4,
    "min": 6,
    "retrograde": false
  },
  "pluto": {
    "lon": 305.330506105851,
    "sign": 10,
    "deg": 5,
    "min": 19,
    "retrograde": true
  },
  "ascendant": {
    "lon": 218.65544804951713,
    "sign": 7,
    "deg": 8,
    "min": 39,
    "retrograde": false
  },
  "medium_coeli": {
    "lon": 136.2245446359748,
    "sign": 4,
    "deg": 16,
    "min": 13,
    "retrograde": false
  }
}