{
  "sun": {
    "lon": 12.546677655658772,
    "sign": 0,
    "deg": 12,
    "min": 32,
    "retrograde": false
  },
  "moon": {
    "lon": 194.82516247234784,
    "sign": 6,
    "deg": 14,
    "min": 49,
    "retrograde": false
  },
  "mercury": {
    "lon": 344.83000435739444,
    "sign": 11,
    "deg": 14,
    "min": 49,
    "retrograde": false
  },
  "venus": {
    "lon": 33.22681169162338,
    "sign": 1,
    "deg": 3,
    "min": 13,
    "retrograde": false
  },
  "mars": {
    "lon": 354.1252199015525,
    "sign": 11,
    "deg": 24,
    "min": 7,
    "retrograde": false
  },
  "jupiter": {
    "lon": 105.86712036452225,
    "sign": 3,
    "deg": 15,
    "min": 52,
    "retrograde": false
  },
  "saturn": {
    "lon": 5.707829252276443,
    "sign": 0,
    "deg": 5,
    "min": 42,
    "retrograde": false
  },
  "uranus": {
    "lon": 58.817198221391614,
    "sign": 1,
    "deg": 28,
    "min": 49,
    "retrograde": false
  },
  "neptune": {
    "lon": 2.252291394363078,
    "sign": 0,
    "deg": 2,
    "min": 15,
    "retrograde": false
  },
  "pluto": {
    "lon": 305.23666257500236,
    "sign": 10,
    "deg": 5,
    "min": 14,
    "retrograde": false
  },
  "ascendant": {
    "lon": 287.68400220428316,
    "sign": 9,
    "deg": 17,
    "min": 41,
    "retrograde": false
  },
  "medium_coeli": {
    "lon": 221.6602448394223,
    "sign": 7,
    "deg": 11,
    "min": 39,
    "retrograde": false
  }
}