{
  "sun": {
    "lon": 57.859985888229005,
    "sign": 1,
    "deg": 27,
    "min": 51,
    "retrograde": false
  },
  "moon": {
    "lon": 85.92781865432076,
    "sign": 2,
    "deg": 25,
    "min": 55,
    "retrograde": false
  },
  "mercury": {
    "lon": 62.98098137294546,
    "sign": 2,
    "deg": 2,
    "min": 58,
    "retrograde": false
  },
  "venus": {
    "lon": 89.71085417608427,
    "sign": 2,
    "deg": 29,
    "min": 42,
    "retrograde": false
  },
  "mars": {
    "lon": 29.901452694309757,
    "sign": 0,
    "deg": 29,
    "min": 54,
    "retrograde": false
  },
  "jupiter": {
    "lon": 111.68929555399052,
    "sign": 3,
    "deg": 21,
    "min": 41,
    "retrograde": false
  },
  "saturn": {
    "lon": 11.034976967022837,
    "sign": 0,
    "deg": 11,
    "min": 2,
    "retrograde": false
  },
  "uranus": {
    "lon": 61.29456846058486,
    "sign": 2,
    "deg": 1,
    "min": 17,
    "retrograde": false
  },
  "neptune": {
    "lon": 3.767193996049906,
    "sign": 0,
    "deg": 3,
    "min": 46,
    "retrograde": false
  },
  "pluto": {
    "lon": 305.47515625622276,
    "sign": 10,
    "deg": 5,
    "min": 28,
    "retrograde": true
  },
  "ascendant": {
    "lon": 180.45800550823196,
    "sign": 6,
    "deg": 0,
    "min": 27,
    "retrograde": false
  },
  "medium_coeli": {
    "lon": 90.52556242811436,
    "sign": 3,
    "deg": 0,
    "min": 31,
    "retrograde": false
  }
}