{
  "sun": {
    "lon": 13.0896374549687,
    "sign": 0,
    "deg": 13,
    "min": 5,
    "retrograde": false
  },
  "moon": {
    "lon": 201.7131395966096,
    "sign": 6,
    "deg": 21,
    "min": 42,
    "retrograde": false
  },
  "mercury": {
    "lon": 345.34016315741246,
    "sign": 11,
    "deg": 15,
    "min": 20,
    "retrograde": false
  },
  "venus": {
    "lon": 33.904273543522265,
    "sign": 1,
    "deg": 3,
    "min": 54,
    "retrograde": false
  },
  "mars": {
    "lon": 354.55568126416614,
    "sign": 11,
    "deg": 24,
    "min": 33,
    "retrograde": false
  },
  "jupiter": {
    "lon": 105.9054571687014,
    "sign": 3,
    "deg": 15,
    "min": 54,
    "retrograde": false
  },
  "saturn": {
    "lon": 5.776222088338513,
    "sign": 0,
    "deg": 5,
    "min": 46,
    "retrograde": false
  },
  "uranus": {
    "lon": 58.841591813293846,
    "sign": 1,
    "deg": 28,
    "min": 50,
    "retrograde": false
  },
  "neptune": {
    "lon": 2.2728769096896064,
    "sign": 0,
    "deg": 2,
    "min": 16,
    "retrograde": false
  },
  "pluto": {
    "lon": 305.2452086340263,
    "sign": 10,
    "deg": 5,
    "min": 14,
    "retrograde": false
  },
  "ascendant": {
    "lon": 154.5197435064839,
    "sign": 5,
    "deg": 4,
    "min": 31,
    "retrograde": false
  },
  "medium_coeli": {
    "lon": 60.191105927588524,
    "sign": 2,
    "deg": 0,
    "min": 11,
    "retrograde": false
  }
}