{
  "sun": {
    "lon": 11.486973257749163,
    "sign": 0,
    "deg": 11,
    "min": 29,
    "retrograde": false
  },
  "moon": {
    "lon": 181.21796248614368,
    "sign": 6,
    "deg": 1,
    "min": 13,
    "retrograde": false
  },
  "mercury": {
    "lon": 343.8793377392245,
    "sign": 11,
    "deg": 13,
    "min": 52,
    "retrograde": false
  },
  "venus": {
    "lon": 31.904672585198476,
    "sign": 1,
    "deg": 1,
    "min": 54,
    "retrograde": false
  },
  "mars": {
    "lon": 353.28514595408103,
    "sign": 11,
    "deg": 23,
    "min": 17,
    "retrograde": false
  },
  "jupiter": {
    "lon": 105.79483172445444,
    "sign": 3,
    "deg": 15,
    "min": 47,
    "retrograde": false
  },
  "saturn": {
    "lon": 5.57429060163621,
    "sign": 0,
    "deg": 5,
    "min": 34,
    "retrograde": false
  },
  "uranus": {
    "lon": 58.77010015758198,
    "sign": 1,
    "deg": 28,
    "min": 46,
    "retrograde": false
  },
  "neptune": {
    "lon": 2.2120614138028776,
    "sign": 0,
    "deg": 2,
    "min": 12,
    "retrograde": false
  },
  "pluto": {
    "lon": 305.2196288617462,
    "sign": 10,
    "deg": 5,
    "min": 13,
    "retrograde": false
  },
  "ascendant": {
    "lon": 261.20840509147723,
    "sign": 8,
    "deg": 21,
    "min": 12,
    "retrograde": false
  },
  "medium_coeli": {
    "lon": 192.4124173730303,
    "sign": 6,
    "deg": 12,
    "min": 24,
    "retrograde": false
  }
}