{
  "sun": {
    "lon": 103.22039636669138,
    "sign": 3,
    "deg": 13,
    "min": 13,
    "retrograde": false
  },
  "moon": {
    "lon": 341.82020422344544,
    "sign": 11,
    "deg": 11,
    "min": 49,
    "retrograde": false
  },
  "mercury": {
    "lon": 115.13969609888055,
    "sign": 3,
    "deg": 25,
    "min": 8,
    "retrograde": true
  },
  "venus": {
    "lon": 144.95263320035193,
    "sign": 4,
    "deg": 24,
    "min": 57,
    "retrograde": false
  },
  "mars": {
    "lon": 64.54633434949865,
    "sign": 2,
    "deg": 4,
    "min": 32,
    "retrograde": false
  },
  "jupiter": {
    "lon": 121.06877528025241,
    "sign": 4,
    "deg": 1,
    "min": 4,
    "retrograde": false
  },
  "saturn": {
    "lon": 14.353952020730043,
    "sign": 0,
    "deg": 14,
    "min": 21,
    "retrograde": false
  },
  "uranus": {
    "lon": 63.9144592748104,
    "sign": 2,
    "deg": 3,
    "min": 54,
    "retrograde": false
  },
  "neptune": {
    "lon": 4.416605373247776,
    "sign": 0,
    "deg": 4,
    "min": 24,
    "retrograde": false
  },
  "pluto": {
    "lon": 304.7875512902557,
    "sign": 10,
    "deg": 4,
    "min": 47,
    "retrograde": true
  },
  "ascendant": {
    "lon": 25.564738505565398,
    "sign": 0,
    "deg": 25,
    "min": 33,
    "retrograde": false
  },
  "medium_coeli": {
    "lon": 284.0937690347823,
    "sign": 9,
    "deg": 14,
    "min": 5,
    "retrograde": false
  }
}