{
  "sun": {
    "lon": 30.180386091641918,
    "sign": 1,
    "deg": 0,
    "min": 10,
    "retrograde": false
  },
  "moon": {
    "lon": 68.56623956079528,
    "sign": 2,
    "deg": 8,
    "min": 33,
    "retrograde": false
  },
  "mercury": {
    "lon": 7.582745487810121,
    "sign": 0,
    "deg": 7,
    "min": 34,
    "retrograde": false
  },
  "venus": {
    "lon": 55.232102240977575,
    "sign": 1,
    "deg": 25,
    "min": 13,
    "retrograde": false
  },
  "mars": {
    "lon": 8.100778769233258,
    "sign": 0,
    "deg": 8,
    "min": 6,
    "retrograde": false
  },
  "jupiter": {
    "lon": 107.5396392197711,
    "sign": 3,
    "deg": 17,
    "min": 32,
    "retrograde": false
  },
  "saturn": {
    "lon": 7.900328132220869,
    "sign": 0,
    "deg": 7,
    "min": 54,
    "retrograde": false
  },
  "uranus": {
    "lon": 59.69057576676551,
    "sign": 1,
    "deg": 29,
    "min": 41,
    "retrograde": false
  },
  "neptune": {
    "lon": 2.9027241438963727,
    "sign": 0,
    "deg": 2,
    "min": 54,
    "retrograde": false
  },
  "pluto": {
    "lon": 305.44708911987345,
    "sign": 10,
    "deg": 5,
    "min": 26,
    "retrograde": false
  },
  "ascendant": {
    "lon": 293.40652410622056,
    "sign": 9,
    "deg": 23,
    "min": 24,
    "retrograde": false
  },
  "medium_coeli": {
    "lon": 226.89802825067378,
    "sign": 7,
    "deg": 16,
    "min": 53,
    "retrograde": false
  }
}