{
  "sun": {
    "lon": 358.9718959779419,
    "sign": 11,
    "deg": 28,
    "min": 58,
    "retrograde": false
  },
  "moon": {
    "lon": 5.7982070390933735,
    "sign": 0,
    "deg": 5,
    "min": 47,
    "retrograde": false
  },
  "mercury": {
    "lon": 338.56700022997876,
    "sign": 11,
    "deg": 8,
    "min": 34,
    "retrograde": true
  },
  "venus": {
    "lon": 16.304451888610533,
    "sign": 0,
    "deg": 16,
    "min": 18,
    "retrograde": false
  },
  "mars": {
    "lon": 343.3762293588042,
    "sign": 11,
    "deg": 13,
    "min": 22,
    "retrograde": false
  },
  "jupiter": {
    "lon": 105.20272279713073,
    "sign": 3,
    "deg": 15,
    "min": 12,
    "retrograde": false
  },
  "saturn": {
    "lon": 3.9985463078307513,
    "sign": 0,
    "deg": 3,
    "min": 59,
    "retrograde": false
  },
  "uranus": {
    "lon": 58.26781786360536,
    "sign": 1,
    "deg": 28,
    "min": 16,
    "retrograde": false
  },
  "neptune": {
    "lon": 1.7342365502549373,
    "sign": 0,
    "deg": 1,
    "min": 44,
    "retrograde": false
  },
  "pluto": {
    "lon": 304.98376268022866,
    "sign": 10,
    "deg": 4,
    "min": 59,
    "retrograde": false
  },
  "ascendant": {
    "lon": 61.55210795756751,
    "sign": 2,
    "deg": 1,
    "min": 33,
    "retrograde": false
  },
  "medium_coeli": {
    "lon": 308.7862312132959,
    "sign": 10,
    "deg": 8,
    "min": 47,
    "retrograde": false
  }
}