{
  "sun": {
    "lon": 1.2048124286726702,
    "sign": 0,
    "deg": 1,
    "min": 12,
    "retrograde": false
  },
  "moon": {
    "lon": 38.00132408953826,
    "sign": 1,
    "deg": 8,
    "min": 0,
    "retrograde": false
  },
  "mercury": {
    "lon": 338.5408568855509,
    "sign": 11,
    "deg": 8,
    "min": 32,
    "retrograde": false
  },
  "venus": {
    "lon": 19.085460298787012,
    "sign": 0,
    "deg": 19,
    "min": 5,
    "retrograde": false
  },
  "mars": {
    "lon": 345.14200246854114,
    "sign": 11,
    "deg": 15,
    "min": 8,
    "retrograde": false
  },
  "jupiter": {
    "lon": 105.27198056885257,
    "sign": 3,
    "deg": 15,
    "min": 16,
    "retrograde": false
  },
  "saturn": {
    "lon": 4.278603497335279,
    "sign": 0,
    "deg": 4,
    "min": 16,
    "retrograde": false
  },
  "uranus": {
    "lon": 58.34963056547242,
    "sign": 1,
    "deg": 28,
    "min": 20,
    "retrograde": false
  },
  "neptune": {
    "lon": 1.8193852887257007,
    "sign": 0,
    "deg": 1,
    "min": 49,
    "retrograde": false
  },
  "pluto": {
    "lon": 305.03022780189116,
    "sign": 10,
    "deg": 5,
    "min": 1,
    "retrograde": false
  },
  "ascendant": {
    "lon": 142.02207460458794,
    "sign": 4,
    "deg": 22,
    "min": 1,
    "retrograde": false
  },
  "medium_coeli": {
    "lon": 44.641707479722015,
    "sign": 1,
    "deg": 14,
    "min": 38,
    "retrograde": false
  }
}