{
  "sun": {
    "lon": 349.83587956624007,
    "sign": 11,
    "deg": 19,
    "min": 50,
    "retrograde": false
  },
  "moon": {
    "lon": 249.12359715519648,
    "sign": 8,
    "deg": 9,
    "min": 7,
    "retrograde": false
  },
  "mercury": {
    "lon": 343.91819298110465,
    "sign": 11,
    "deg": 13,
    "min": 55,
    "retrograde": true
  },
  "venus": {
    "lon": 4.93524960060912,
    "sign": 0,
    "deg": 4,
    "min": 56,
    "retrograde": false
  },
  "mars": {
    "lon": 336.16323331601205,
    "sign": 11,
    "deg": 6,
    "min": 9,
    "retrograde": false
  },
  "jupiter": {
    "lon": 105.08824142308508,
    "sign": 3,
    "deg": 15,
    "min": 5,
    "retrograde": true
  },
  "saturn": {
    "lon": 2.864191881532911,
    "sign": 0,
    "deg": 2,
    "min": 51,
    "retrograde": false
  },
  "uranus": {
    "lon": 57.97092189243967,
    "sign": 1,
    "deg": 27,
    "min": 58,
    "retrograde": false
  },
  "neptune": {
    "lon": 1.3891097812339601,
    "sign": 0,
    "deg": 1,
    "min": 23,
    "retrograde": false
  },
  "pluto": {
    "lon": 304.7753057552623,
    "sign": 10,
    "deg": 4,
    "min": 46,
    "retrograde": false
  },
  "ascendant": {
    "lon": 317.1069964685694,
    "sign": 10,
    "deg": 17,
    "min": 6,
    "retrograde": false
  },
  "medium_coeli": {
    "lon": 245.11793083184887,
    "sign": 8,
    "deg": 5,
    "min": 7,
    "retrograde": false
  }
}