{
  "sun": {
    "lon": 98.38329076668357,
    "sign": 3,
    "deg": 8,
    "min": 22,
    "retrograde": false
  },
  "moon": {
    "lon": 279.9463095286439,
    "sign": 9,
    "deg": 9,
    "min": 56,
    "retrograde": false
  },
  "mercury": {
    "lon": 116.2509827034736,
    "sign": 3,
    "deg": 26,
    "min": 15,
    "retrograde": true
  },
  "venus": {
    "lon": 139.21741977005357,
    "sign": 4,
    "deg": 19,
    "min": 13,
    "retrograde": false
  },
  "mars": {
    "lon": 60.94675590733876,
    "sign": 2,
    "deg": 0,
    "min": 56,
    "retrograde": false
  },
  "jupiter": {
    "lon": 119.97770132612693,
    "sign": 3,
    "deg": 29,
    "min": 58,
    "retrograde": false
  },
  "saturn": {
    "lon": 14.149173850006441,
    "sign": 0,
    "deg": 14,
    "min": 8,
    "retrograde": false
  },
  "uranus": {
    "lon": 63.664357381659286,
    "sign": 2,
    "deg": 3,
    "min": 39,
    "retrograde": false
  },
  "neptune": {
    "lon": 4.403282924122023,
    "sign": 0,
    "deg": 4,
    "min": 24,
    "retrograde": false
  },
  "pluto": {
    "lon": 304.893421655659,
    "sign": 10,
    "deg": 4,
    "min": 53,
    "retrograde": true
  },
  "ascendant": {
    "lon": 332.6225491649112,
    "sign": 11,
    "deg": 2,
    "min": 37,
    "retrograde": false
  },
  "medium_coeli": {
    "lon": 254.84457320958782,
    "sign": 8,
    "deg": 14,
    "min": 50,
    "retrograde": false
  }
}