{
  "sun": {
    "lon": 359.52573580066536,
    "sign": 11,
    "deg": 29,
    "min": 31,
    "retrograde": false
  },
  "moon": {
    "lon": 13.696150847329006,
    "sign": 0,
    "deg": 13,
    "min": 41,
    "retrograde": false
  },
  "mercury": {
    "lon": 338.51353456106574,
    "sign": 11,
    "deg": 8,
    "min": 30,
    "retrograde": true
  },
  "venus": {
    "lon": 16.99414189834357,
    "sign": 0,
    "deg": 16,
    "min": 59,
    "retrograde": false
  },
  "mars": {
    "lon": 343.8141029021149,
    "sign": 11,
    "deg": 13,
    "min": 48,
    "retrograde": false
  },
  "jupiter": {
    "lon": 105.21839198673857,
    "sign": 3,
    "deg": 15,
    "min": 13,
    "retrograde": false
  },
  "saturn": {
    "lon": 4.067927810620364,
    "sign": 0,
    "deg": 4,
    "min": 4,
    "retrograde": false
  },
  "uranus": {
    "lon": 58.2877745172987,
    "sign": 1,
    "deg": 28,
    "min": 17,
    "retrograde": false
  },
  "neptune": {
    "lon": 1.7553371424135038,
    "sign": 0,
    "deg": 1,
    "min": 45,
    "retrograde": false
  },
  "pluto": {
    "lon": 304.99545282275415,
    "sign": 10,
    "deg": 4,
    "min": 59,
    "retrograde": false
  },
  "ascendant": {
    "lon": 229.3411887570693,
    "sign": 7,
    "deg": 19,
    "min": 20,
    "retrograde": false
  },
  "medium_coeli": {
    "lon": 150.1828761428723,
    "sign": 5,
    "deg": 0,
    "min": 10,
    "retrograde": false
  }
}