{
  "sun": {
    "lon": 13.563992897920206,
    "sign": 0,
    "deg": 13,
    "min": 33,
    "retrograde": false
  },
  "moon": {
    "lon": 207.6855272469337,
    "sign": 6,
    "deg": 27,
    "min": 41,
    "retrograde": false
  },
  "mercury": {
    "lon": 345.7981962506773,
    "sign": 11,
    "deg": 15,
    "min": 47,
    "retrograde": false
  },
  "venus": {
    "lon": 34.496154747659816,
    "sign": 1,
    "deg": 4,
    "min": 29,
    "retrograde": false
  },
  "mars": {
    "lon": 354.9317683592115,
    "sign": 11,
    "deg": 24,
    "min": 55,
    "retrograde": false
  },
  "jupiter": {
    "lon": 105.93966685520576,
    "sign": 3,
    "deg": 15,
    "min": 56,
    "retrograde": false
  },
  "saturn": {
    "lon": 5.835955076239785,
    "sign": 0,
    "deg": 5,
    "min": 50,
    "retrograde": false
  },
  "uranus": {
    "lon": 58.86304764335928,
    "sign": 1,
    "deg": 28,
    "min": 51,
    "retrograde": false
  },
  "neptune": {
    "lon": 2.2908456442612044,
    "sign": 0,
    "deg": 2,
    "min": 17,
    "retrograde": false
  },
  "pluto": {
    "lon": 305.2525742548688,
    "sign": 10,
    "deg": 5,
    "min": 15,
    "retrograde": false
  },
  "ascendant": {
    "lon": 302.021377396818,
    "sign": 10,
    "deg": 2,
    "min": 1,
    "retrograde": false
  },
  "medium_coeli": {
    "lon": 234.1146022376353,
    "sign": 7,
    "deg": 24,
    "min": 6,
    "retrograde": false
  }
}