{
  "sun": {
    "lon": 27.42992135547985,
    "sign": 0,
    "deg": 27,
    "min": 25,
    "retrograde": false
  },
  "moon": {
    "lon": 26.68798117564417,
    "sign": 0,
    "deg": 26,
    "min": 41,
    "retrograde": false
  },
  "mercury": {
    "lon": 3.3155645111953667,
    "sign": 0,
    "deg": 3,
    "min": 18,
    "retrograde": false
  },
  "venus": {
    "lon": 51.79971015523014,
    "sign": 1,
    "deg": 21,
    "min": 47,
    "retrograde": false
  },
  "mars": {
    "lon": 5.922939594104933,
    "sign": 0,
    "deg": 5,
    "min": 55,
    "retrograde": false
  },
  "jupiter": {
    "lon": 107.22301755454886,
    "sign": 3,
    "deg": 17,
    "min": 13,
    "retrograde": false
  },
  "saturn": {
    "lon": 7.564210480490192,
    "sign": 0,
    "deg": 7,
    "min": 33,
    "retrograde": false
  },
  "uranus": {
    "lon": 59.544328191803835,
    "sign": 1,
    "deg": 29,
    "min": 32,
    "retrograde": false
  },
  "neptune": {
    "lon": 2.804617689606166,
    "sign": 0,
    "deg": 2,
    "min": 48,
    "retrograde": false
  },
  "pluto": {
    "lon": 305.42376047676095,
    "sign": 10,
    "deg": 5,
    "min": 25,
    "retrograde": false
  },
  "ascendant": {
    "lon": 31.216216718591433,
    "sign": 1,
    "deg": 1,
    "min": 12,
    "retrograde": false
  },
  "medium_coeli": {
    "lon": 287.44787427920227,
    "sign": 9,
    "deg": 17,
    "min": 26,
    "retrograde": false
  }
}