{
  "sun": {
    "lon": 98.6990669402619,
    "sign": 3,
    "deg": 8,
    "min": 41,
    "retrograde": false
  },
  "moon": {
    "lon": 283.8981805408443,
    "sign": 9,
    "deg": 13,
    "min": 53,
    "retrograde": false
  },
  "mercury": {
    "lon": 116.23641101840626,
    "sign": 3,
    "deg": 26,
    "min": 14,
    "retrograde": true
  },
  "venus": {
    "lon": 139.59351302638117,
    "sign": 4,
    "deg": 19,
    "min": 35,
    "retrograde": false
  },
  "mars": {
    "lon": 61.18256582950483,
    "sign": 2,
    "deg": 1,
    "min": 10,
    "retrograde": false
  },
  "jupiter": {
    "lon": 120.04853048644513,
    "sign": 4,
    "deg": 0,
    "min": 2,
    "retrograde": false
  },
  "saturn": {
    "lon": 14.163783774788774,
    "sign": 0,
    "deg": 14,
    "min": 9,
    "retrograde": false
  },
  "uranus": {
    "lon": 63.68102601174366,
    "sign": 2,
    "deg": 3,
    "min": 40,
    "retrograde": false
  },
  "neptune": {
    "lon": 4.404586564558135,
    "sign": 0,
    "deg": 4,
    "min": 24,
    "retrograde": false
  },
  "pluto": {
    "lon": 304.88668123449094,
    "sign": 10,
    "deg": 4,
    "min": 53,
    "retrograde": true
  },
  "ascendant": {
    "lon": 119.08001391091017,
    "sign": 3,
    "deg": 29,
    "min": 4,
    "retrograde": false
  },
  "medium_coeli": {
    "lon": 14.263390080470929,
    "sign": 0,
    "deg": 14,
    "min": 15,
    "retrograde": false
  }
}