{
  "sun": {
    "lon": 86.65452962968607,
    "sign": 2,
    "deg": 26,
    "min": 39,
    "retrograde": false
  },
  "moon": {
    "lon": 125.02430650093544,
    "sign": 4,
    "deg": 5,
    "min": 1,
    "retrograde": false
  },
  "mercury": {
    "lon": 111.04581819338031,
    "sign": 3,
    "deg": 21,
    "min": 2,
    "retrograde": false
  },
  "venus": {
    "lon": 125.10912876602572,
    "sign": 4,
    "deg": 5,
    "min": 6,
    "retrograde": false
  },
  "mars": {
    "lon": 52.113563388331094,
    "sign": 1,
    "deg": 22,
    "min": 6,
    "retrograde": false
  },
  "jupiter": {
    "lon": 117.3974366543726,
    "sign": 3,
    "deg": 27,
    "min": 23,
    "retrograde": false
  },
  "saturn": {
    "lon": 13.489954217248611,
    "sign": 0,
    "deg": 13,
    "min": 29,
    "retrograde": false
  },
  "uranus": {
    "lon": 63.01719208997529,
    "sign": 2,
    "deg": 3,
    "min": 1,
    "retrograde": false
  },
  "neptune": {
    "lon": 4.313267178675856,
    "sign": 0,
    "deg": 4,
    "min": 18,
    "retrograde": false
  },
  "pluto": {
    "lon": 305.1246490030812,
    "sign": 10,
    "deg": 5,
    "min": 7,
    "retrograde": true
  },
  "ascendant": {
    "lon": 216.29702158507519,
    "sign": 7,
    "deg": 6,
    "min": 17,
    "retrograde": false
  },
  "medium_coeli": {
    "lon": 133.21940304912326,
    "sign": 4,
    "deg": 13,
    "min": 13,
    "retrograde": false
  }
}