{
  "sun": {
    "lon": 352.65112708290326,
    "sign": 11,
    "deg": 22,
    "min": 39,
    "retrograde": false
  },
  "moon": {
    "lon": 282.8233765111852,
    "sign": 9,
    "deg": 12,
    "min": 49,
    "retrograde": false
  },
  "mercury": {
    "lon": 341.450429373048,
    "sign": 11,
    "deg": 11,
    "min": 27,
    "retrograde": true
  },
  "venus": {
    "lon": 8.43722667661173,
    "sign": 0,
    "deg": 8,
    "min": 26,
    "retrograde": false
  },
  "mars": {
    "lon": 338.3837316896025,
    "sign": 11,
    "deg": 8,
    "min": 23,
    "retrograde": false
  },
  "jupiter": {
    "lon": 105.09450440570583,
    "sign": 3,
    "deg": 15,
    "min": 5,
    "retrograde": false
  },
  "saturn": {
    "lon": 3.2113356840044585,
    "sign": 0,
    "deg": 3,
    "min": 12,
    "retrograde": false
  },
  "uranus": {
    "lon": 58.05578971736956,
    "sign": 1,
    "deg": 28,
    "min": 3,
    "retrograde": false
  },
  "neptune": {
    "lon": 1.494705898685602,
    "sign": 0,
    "deg": 1,
    "min": 29,
    "retrograde": false
  },
  "pluto": {
    "lon": 304.84256392920037,
    "sign": 10,
    "deg": 4,
    "min": 50,
    "retrograde": false
  },
  "ascendant": {
    "lon": 252.3673065790383,
    "sign": 8,
    "deg": 12,
    "min": 22,
    "retrograde": false
  },
  "medium_coeli": {
    "lon": 181.04820725289454,
    "sign": 6,
    "deg": 1,
    "min": 2,
    "retrograde": false
  }
}