{
  "sun": {
    "lon": 68.14224288117279,
    "sign": 2,
    "deg": 8,
    "min": 8,
    "retrograde": false
  },
  "moon": {
    "lon": 227.6720152603018,
    "sign": 7,
    "deg": 17,
    "min": 40,
    "retrograde": false
  },
  "mercury": {
    "lon": 84.71175666810554,
    "sign": 2,
    "deg": 24,
    "min": 42,
    "retrograde": false
  },
  "venus": {
    "lon": 102.43993245306838,
    "sign": 3,
    "deg": 12,
    "min": 26,
    "retrograde": false
  },
  "mars": {
    "lon": 37.904640440250006,
    "sign": 1,
    "deg": 7,
    "min": 54,
    "retrograde": false
  },
  "jupiter": {
    "lon": 113.59969492312418,
    "sign": 3,
    "deg": 23,
    "min": 35,
    "retrograde": false
  },
  "saturn": {
    "lon": 12.029906304279514,
    "sign": 0,
    "deg": 12,
    "min": 1,
    "retrograde": false
  },
  "uranus": {
    "lon": 61.918829698322845,
    "sign": 2,
    "deg": 1,
    "min": 55,
    "retrograde": false
  },
  "neptune": {
    "lon": 4.010992267758182,
    "sign": 0,
    "deg": 4,
    "min": 0,
    "retrograde": false
  },
  "pluto": {
    "lon": 305.39076006298797,
    "sign": 10,
    "deg": 5,
    "min": 23,
    "retrograde": true
  },
  "ascendant": {
    "lon": 101.8232360910147,
    "sign": 3,
    "deg": 11,
    "min": 49,
    "retrograde": false
  },
  "medium_coeli": {
    "lon": 351.4177447209902,
    "sign": 11,
    "deg": 21,
    "min": 25,
    "retrograde": false
  }
}