{
  "sun": {
    "lon": 13.863737851997918,
    "sign": 0,
    "deg": 13,
    "min": 51,
    "retrograde": false
  },
  "moon": {
    "lon": 211.4383269609089,
    "sign": 7,
    "deg": 1,
    "min": 26,
    "retrograde": false
  },
  "mercury": {
    "lon": 346.0934250711845,
    "sign": 11,
    "deg": 16,
    "min": 5,
    "retrograde": false
  },
  "venus": {
    "lon": 34.870172139469865,
    "sign": 1,
    "deg": 4,
    "min": 52,
    "retrograde": false
  },
  "mars": {
    "lon": 355.16942420445133,
    "sign": 11,
    "deg": 25,
    "min": 10,
    "retrograde": false
  },
  "jupiter": {
    "lon": 105.9616275833034,
    "sign": 3,
    "deg": 15,
    "min": 57,
    "retrograde": false
  },
  "saturn": {
    "lon": 5.873690702447842,
    "sign": 0,
    "deg": 5,
    "min": 52,
    "retrograde": false
  },
  "uranus": {
    "lon": 58.876674687863805,
    "sign": 1,
    "deg": 28,
    "min": 52,
    "retrograde": false
  },
  "neptune": {
    "lon": 2.3021922166549187,
    "sign": 0,
    "deg": 2,
    "min": 18,
    "retrograde": false
  },
  "pluto": {
    "lon": 305.2571801457074,
    "sign": 10,
    "deg": 5,
    "min": 15,
    "retrograde": false
  },
  "ascendant": {
    "lon": 92.5784925455274,
    "sign": 3,
    "deg": 2,
    "min": 34,
    "retrograde": false
  },
  "medium_coeli": {
    "lon": 340.00876268974145,
    "sign": 11,
    "deg": 10,
    "min": 0,
    "retrograde": false
  }
}