{
  "sun": {
    "lon": 50.82905215118969,
    "sign": 1,
    "deg": 20,
    "min": 49,
    "retrograde": false
  },
  "moon": {
    "lon": 340.0870117058269,
    "sign": 11,
    "deg": 10,
    "min": 5,
    "retrograde": false
  },
  "mercury": {
    "lon": 47.137673353329966,
    "sign": 1,
    "deg": 17,
    "min": 8,
    "retrograde": false
  },
  "venus": {
    "lon": 80.97574803550923,
    "sign": 2,
    "deg": 20,
    "min": 58,
    "retrograde": false
  },
  "mars": {
    "lon": 24.393622677537753,
    "sign": 0,
    "deg": 24,
    "min": 23,
    "retrograde": false
  },
  "jupiter": {
    "lon": 110.48619799973068,
    "sign": 3,
    "deg": 20,
    "min": 29,
    "retrograde": false
  },
  "saturn": {
    "lon": 10.293123103669203,
    "sign": 0,
    "deg": 10,
    "min": 17,
    "retrograde": false
  },
  "uranus": {
    "lon": 60.871238969934836,
    "sign": 2,
    "deg": 0,
    "min": 52,
    "retrograde": false
  },
  "neptune": {
    "lon": 3.5732902185154694,
    "sign": 0,
    "deg": 3,
    "min": 34,
    "retrograde": false
  },
  "pluto": {
    "lon": 305.50382426575453,
    "sign": 10,
    "deg": 5,
    "min": 30,
    "retrograde": true
  },
  "ascendant": {
    "lon": 91.53806723509744,
    "sign": 3,
    "deg": 1,
    "min": 32,
    "retrograde": false
  },
  "medium_coeli": {
    "lon": 338.77909627581806,
    "sign": 11,
    "deg": 8,
    "min": 46,
    "retrograde": false
  }
}