{
  "sun": {
    "lon": 33.30278206610283,
    "sign": 1,
    "deg": 3,
    "min": 18,
    "retrograde": false
  },
  "moon": {
    "lon": 114.89200453278353,
    "sign": 3,
    "deg": 24,
    "min": 53,
    "retrograde": false
  },
  "mercury": {
    "lon": 12.712114293740445,
    "sign": 0,
    "deg": 12,
    "min": 42,
    "retrograde": false
  },
  "venus": {
    "lon": 59.128712100356815,
    "sign": 1,
    "deg": 29,
    "min": 7,
    "retrograde": false
  },
  "mars": {
    "lon": 10.57166015986961,
    "sign": 0,
    "deg": 10,
    "min": 34,
    "retrograde": false
  },
  "jupiter": {
    "lon": 107.92247680148678,
    "sign": 3,
    "deg": 17,
    "min": 55,
    "retrograde": false
  },
  "saturn": {
    "lon": 8.278085831745123,
    "sign": 0,
    "deg": 8,
    "min": 16,
    "retrograde": false
  },
  "uranus": {
    "lon": 59.860477200577094,
    "sign": 1,
    "deg": 29,
    "min": 51,
    "retrograde": false
  },
  "neptune": {
    "lon": 3.0121213923578716,
    "sign": 0,
    "deg": 3,
    "min": 0,
    "retrograde": false
  },
  "pluto": {
    "lon": 305.4692234231133,
    "sign": 10,
    "deg": 5,
    "min": 28,
    "retrograde": false
  },
  "ascendant": {
    "lon": 46.39517267664039,
    "sign": 1,
    "deg": 16,
    "min": 23,
    "retrograde": false
  },
  "medium_coeli": {
    "lon": 297.2769245255116,
    "sign": 9,
    "deg": 27,
    "min": 16,
    "retrograde": false
  }
}