{
  "sun": {
    "lon": 22.755369586091927,
    "sign": 0,
    "deg": 22,
    "min": 45,
    "retrograde": false
  },
  "moon": {
    "lon": 320.9102037578073,
    "sign": 10,
    "deg": 20,
    "min": 54,
    "retrograde": false
  },
  "mercury": {
    "lon": 356.61998195324566,
    "sign": 11,
    "deg": 26,
    "min": 37,
    "retrograde": false
  },
  "venus": {
    "lon": 45.966215663708134,
    "sign": 1,
    "deg": 15,
    "min": 57,
    "retrograde": false
  },
  "mars": {
    "lon": 2.2191826179830083,
    "sign": 0,
    "deg": 2,
    "min": 13,
    "retrograde": false
  },
  "jupiter": {
    "lon": 106.73089628087544,
    "sign": 3,
    "deg": 16,
    "min": 43,
    "retrograde": false
  },
  "saturn": {
    "lon": 6.986943672483601,
    "sign": 0,
    "deg": 6,
    "min": 59,
    "retrograde": false
  },
  "uranus": {
    "lon": 59.30380487476535,
    "sign": 1,
    "deg": 29,
    "min": 18,
    "retrograde": false
  },
  "neptune": {
    "lon": 2.6346675633982417,
    "sign": 0,
    "deg": 2,
    "min": 38,
    "retrograde": false
  },
  "pluto": {
    "lon": 305.37601652154456,
    "sign": 10,
    "deg": 5,
    "min": 22,
    "retrograde": false
  },
  "ascendant": {
    "lon": 113.70919369928984,
    "sign": 3,
    "deg": 23,
    "min": 42,
    "retrograde": false
  },
  "medium_coeli": {
    "lon": 7.031798408116203,
    "sign": 0,
    "deg": 7,
    "min": 1,
    "retrograde": false
  }
}